{
  "title": "",
  "url": "https://documentacao.senior.com.br/gestaoempresarialerp/5.10.4/#menu_controladoria/geracao_fato_contabil.htm%3FTocPath%3DSegmentos%7CCompliance%7CConfigura%25C3%25A7%25C3%25B5es%2520para%2520c%25C3%25A1lculos%2520fiscais%2520%7C_____8",
  "breadcrumb": [
    "GESTAOEMPRESARIALERP",
    "Geração de fatos contábeis entre módulos do ERP"
  ],
  "total_chars": 12681,
  "headers_count": 4,
  "paragraphs_count": 55,
  "lists_count": 3,
  "links_count": 25,
  "scraped_at": "2026-01-21T15:35:04.478639"
}