{
  "title": "",
  "url": "https://documentacao.senior.com.br/tecnologia/5.10.4/#recursos-de-interface/configuracoes-internacionais/finternationalcfg.htm%3FTocPath%3DTecnologia%7CFerramentas%2520de%2520Apoio%7CRecursos%2520da%2520Interface%2520do%2520Sistema%7CConfigura%25C3%25A7%25C3%25B5es%2520Internacionais%7C_____1",
  "breadcrumb": [
    "TECNOLOGIA",
    "Configurações Internacionais"
  ],
  "total_chars": 13782,
  "headers_count": 7,
  "paragraphs_count": 56,
  "lists_count": 1,
  "links_count": 22,
  "scraped_at": "2026-01-21T16:17:44.155989"
}